<?xml version="1.0" encoding="utf-8"?>
<LinearLayout xmlns:android="http://schemas.android.com/apk/res/android"
    android:layout_width="fill_parent"
    android:layout_height="fill_parent"
    android:orientation="vertical" >

    <TextView
        android:id="@+id/basliktxt"
        android:layout_width="match_parent"
        android:layout_height="wrap_content"
        android:text="ADMIN"
        android:textSize="20dp"
        android:gravity="center" >
    </TextView>
    <TextView
        android:id="@+id/textView1"
        android:layout_width="match_parent"
        android:layout_height="wrap_content"
        android:text="Kullanici Ekleme"
        android:gravity="center">
    </TextView>
    <LinearLayout
        android:layout_width="match_parent"
        android:layout_height="wrap_content"
        android:orientation="horizontal" >
    	<EditText
            android:id="@+id/editText1"
            android:layout_width="wrap_content"
            android:layout_height="wrap_content"
            android:hint="User"
            android:nextFocusRight="@+id/editText2" >
        </EditText>
    	<EditText
            android:id="@+id/editText2"
            android:layout_width="wrap_content"
            android:layout_height="wrap_content"
            android:hint="Sifre"
            android:nextFocusRight="@+id/editText3" >
        </EditText>
        <EditText
            android:id="@+id/editText3"
            android:layout_width="wrap_content"
            android:layout_height="wrap_content"
            android:hint="Yetki">
        </EditText>         
    </LinearLayout>
    <Button
    android:id="@+id/button1"
    android:layout_width="wrap_content"
    android:layout_height="wrap_content"
    android:text="Ekle" >
	</Button>
    <TextView
    android:id="@+id/textView2"
    android:layout_width="match_parent"
    android:layout_height="wrap_content"
    android:text="Urun Ekleme"  
    android:gravity="center">   
	</TextView>
     <LinearLayout
        android:layout_width="match_parent"
        android:layout_height="wrap_content"
        android:orientation="horizontal" >
    	<EditText
            android:id="@+id/editText4"
            android:layout_width="wrap_content"
            android:layout_height="wrap_content"
            android:hint="Urun Adi"
            android:nextFocusRight="@+id/editText4" >
        </EditText>
    	<EditText
            android:id="@+id/editText5"
            android:layout_width="wrap_content"
            android:layout_height="wrap_content"
            android:hint="Fiyati">
        </EditText>  
    </LinearLayout>
    <Button
    android:id="@+id/button2"
    android:layout_width="wrap_content"
    android:layout_height="wrap_content"
    android:text="Ekle" >
	</Button>
    <TextView
    android:id="@+id/textView3"
    android:layout_width="match_parent"
    android:layout_height="wrap_content"
    android:text="Kullanici Silme"  
    android:gravity="center">   
    </TextView>
     <LinearLayout
        android:layout_width="match_parent"
        android:layout_height="wrap_content"
        android:orientation="horizontal" >
        <Spinner
            android:id="@+id/spinner1"
            android:layout_width="wrap_content"
            android:layout_height="wrap_content" >
        </Spinner>
            <Button
            android:id="@+id/button3"
            android:layout_width="wrap_content"
            android:layout_height="wrap_content"
            android:text="Sil" >
            </Button>
    </LinearLayout>
        <TextView
    android:id="@+id/textView3"
    android:layout_width="match_parent"
    android:layout_height="wrap_content"
    android:text="Urun Silme"  
    android:gravity="center">   
    </TextView>
         <LinearLayout
        android:layout_width="match_parent"
        android:layout_height="wrap_content"
        android:orientation="horizontal" >
        <Spinner
            android:id="@+id/spinner2"
            android:layout_width="wrap_content"
            android:layout_height="wrap_content" >
        </Spinner>
            <Button
            android:id="@+id/button4"
            android:layout_width="wrap_content"
            android:layout_height="wrap_content"
            android:text="Sil" >
            </Button>
    </LinearLayout>

</LinearLayout>